odoo/addons/l10n_es_pos/README.rst
odoo/addons/l10n_es_pos/__init__.py
odoo/addons/l10n_es_pos/__manifest__.py
odoo/addons/l10n_es_pos/hooks.py
odoo/addons/l10n_es_pos/i18n/ca.po
odoo/addons/l10n_es_pos/i18n/ca_ES.po
odoo/addons/l10n_es_pos/i18n/es.po
odoo/addons/l10n_es_pos/i18n/l10n_es_pos.pot
odoo/addons/l10n_es_pos/migrations/14.0.2.1.0/pre-migration.py
odoo/addons/l10n_es_pos/models/__init__.py
odoo/addons/l10n_es_pos/models/ir_sequence.py
odoo/addons/l10n_es_pos/models/pos_config.py
odoo/addons/l10n_es_pos/models/pos_order.py
odoo/addons/l10n_es_pos/readme/CONFIGURE.rst
odoo/addons/l10n_es_pos/readme/CONTRIBUTORS.rst
odoo/addons/l10n_es_pos/readme/DESCRIPTION.rst
odoo/addons/l10n_es_pos/readme/INSTALL.rst
odoo/addons/l10n_es_pos/readme/ROADMAP.rst
odoo/addons/l10n_es_pos/static/description/icon.png
odoo/addons/l10n_es_pos/static/description/index.html
odoo/addons/l10n_es_pos/static/src/js/PaymentScreen.js
odoo/addons/l10n_es_pos/static/src/js/models.js
odoo/addons/l10n_es_pos/static/src/js/Screens/OrderManagementScreen/OrderManagementControlPanel.js
odoo/addons/l10n_es_pos/static/src/js/Screens/OrderManagementScreen/OrderRow.js
odoo/addons/l10n_es_pos/static/src/xml/pos.xml
odoo/addons/l10n_es_pos/static/src/xml/Screens/OrderManagementScreen/OrderList.xml
odoo/addons/l10n_es_pos/static/src/xml/Screens/OrderManagementScreen/OrderRow.xml
odoo/addons/l10n_es_pos/views/pos_templates.xml
odoo/addons/l10n_es_pos/views/pos_views.xml
odoo14_addon_l10n_es_pos-14.0.3.3.0.dist-info/METADATA
odoo14_addon_l10n_es_pos-14.0.3.3.0.dist-info/WHEEL
odoo14_addon_l10n_es_pos-14.0.3.3.0.dist-info/top_level.txt
odoo14_addon_l10n_es_pos-14.0.3.3.0.dist-info/RECORD
