Metadata-Version: 2.1
Name: odoo14-addon-l10n_es_pos
Version: 14.0.3.3.0
Summary: Punto de venta adaptado a la legislación española
Home-page: https://github.com/OCA/l10n-spain
Author: Tecnativa, Aselcis Consulting, Acysos S.L., Odoo Community Association (OCA)
Author-email: support@odoo-community.org
License: AGPL-3
Classifier: Programming Language :: Python
Classifier: Framework :: Odoo
Classifier: Framework :: Odoo :: 14.0
Classifier: License :: OSI Approved :: GNU Affero General Public License v3
Requires-Python: >=3.6
Requires-Dist: odoo <14.1dev,>=14.0a
